cb0tcc/__init__.py
cb0tcc/amain.py
cb0tcc/error.py
cb0tcc/main.py
cb0tcc.py-0.0.7.dist-info/LICENSE
cb0tcc.py-0.0.7.dist-info/METADATA
cb0tcc.py-0.0.7.dist-info/WHEEL
cb0tcc.py-0.0.7.dist-info/top_level.txt
cb0tcc.py-0.0.7.dist-info/RECORD
