Metadata-Version: 2.1
Name: cb0tcc.py
Version: 0.0.7
Summary: This can create shorturl.
Home-page: https://github.com/tuna2134/cb0t.py
Author: DMS
Author-email: masato190411@gmail.com
License: UNKNOWN
Platform: UNKNOWN
Classifier: Programming Language :: Python :: 3.8
Classifier: License :: OSI Approved :: MIT License
Classifier: Operating System :: OS Independent
Requires-Dist: requests
Requires-Dist: aiohttp
